README.md
setup.cfg
setup.py
nm_distributions/Binomialdistribution.py
nm_distributions/Gaussiandistribution.py
nm_distributions/Generaldistribution.py
nm_distributions/__init__.py
nm_distributions.egg-info/PKG-INFO
nm_distributions.egg-info/SOURCES.txt
nm_distributions.egg-info/dependency_links.txt
nm_distributions.egg-info/not-zip-safe
nm_distributions.egg-info/top_level.txt