Metadata-Version: 1.0
Name: nm-distributions
Version: 0.1
Summary: Gaussian and Binomial distributions
Home-page: UNKNOWN
Author: Nirisha Manandhar
Author-email: nirishamanandhar@gmail.com
License: UNKNOWN
Platform: UNKNOWN
